{
  "period": {
    "start": "2026-06-10",
    "end": "2026-06-23"
  },
  "channels": [
    {
      "channel": "Direct",
      "sessions": 5248,
      "pdp": 1737,
      "atc": 83,
      "co": 44,
      "buy": 27,
      "pdp_rate": 33.1,
      "atc_rate": 1.58,
      "cvr": 0.514
    },
    {
      "channel": "Organic Search",
      "sessions": 2756,
      "pdp": 1254,
      "atc": 37,
      "co": 22,
      "buy": 23,
      "pdp_rate": 45.5,
      "atc_rate": 1.34,
      "cvr": 0.835
    },
    {
      "channel": "Paid Search",
      "sessions": 2566,
      "pdp": 1228,
      "atc": 49,
      "co": 30,
      "buy": 27,
      "pdp_rate": 47.9,
      "atc_rate": 1.91,
      "cvr": 1.052
    },
    {
      "channel": "Referral",
      "sessions": 951,
      "pdp": 332,
      "atc": 12,
      "co": 7,
      "buy": 5,
      "pdp_rate": 34.9,
      "atc_rate": 1.26,
      "cvr": 0.526
    },
    {
      "channel": "Other",
      "sessions": 689,
      "pdp": 205,
      "atc": 7,
      "co": 3,
      "buy": 2,
      "pdp_rate": 29.8,
      "atc_rate": 1.02,
      "cvr": 0.29
    },
    {
      "channel": "Email",
      "sessions": 242,
      "pdp": 92,
      "atc": 5,
      "co": 2,
      "buy": 2,
      "pdp_rate": 38.0,
      "atc_rate": 2.07,
      "cvr": 0.826
    },
    {
      "channel": "LINE",
      "sessions": 223,
      "pdp": 67,
      "atc": 5,
      "co": 2,
      "buy": 1,
      "pdp_rate": 30.0,
      "atc_rate": 2.24,
      "cvr": 0.448
    },
    {
      "channel": "Social",
      "sessions": 144,
      "pdp": 55,
      "atc": 9,
      "co": 3,
      "buy": 2,
      "pdp_rate": 38.2,
      "atc_rate": 6.25,
      "cvr": 1.389
    }
  ]
}