{
  "channels": [
    {
      "channel": "Direct",
      "sessions": 5355,
      "orders": 34,
      "sales": 522005,
      "cvr": 0.006349206349206349
    },
    {
      "channel": "Paid Search",
      "sessions": 1241,
      "orders": 8,
      "sales": 141075,
      "cvr": 0.0064464141821112
    },
    {
      "channel": "Organic Search",
      "sessions": 1162,
      "orders": 13,
      "sales": 261140,
      "cvr": 0.011187607573149742
    },
    {
      "channel": "Other",
      "sessions": 627,
      "orders": 5,
      "sales": 95920,
      "cvr": 0.007974481658692184
    },
    {
      "channel": "Referral",
      "sessions": 362,
      "orders": 3,
      "sales": 42625,
      "cvr": 0.008287292817679558
    },
    {
      "channel": "LINE",
      "sessions": 246,
      "orders": 3,
      "sales": 29095,
      "cvr": 0.012195121951219513
    },
    {
      "channel": "Email",
      "sessions": 204,
      "orders": 5,
      "sales": 67375,
      "cvr": 0.024509803921568627
    },
    {
      "channel": "Social",
      "sessions": 45,
      "orders": 1,
      "sales": 28050,
      "cvr": 0.022222222222222223
    }
  ],
  "trend": {
    "weeks": [
      "2026-W18",
      "2026-W19",
      "2026-W20",
      "2026-W21",
      "2026-W22",
      "2026-W23",
      "2026-W24",
      "2026-W25",
      "2026-W26",
      "2026-W27"
    ],
    "series": [
      {
        "channel": "Direct",
        "sessions": [
          2514,
          3680,
          2311,
          3473,
          3059,
          3482,
          2990,
          2491,
          4165,
          5598
        ]
      },
      {
        "channel": "Paid Search",
        "sessions": [
          1814,
          1993,
          1495,
          1686,
          1442,
          1370,
          1367,
          1372,
          1261,
          1383
        ]
      },
      {
        "channel": "Organic Search",
        "sessions": [
          1553,
          1754,
          1275,
          1708,
          1635,
          1447,
          1486,
          1415,
          1334,
          1338
        ]
      },
      {
        "channel": "Referral",
        "sessions": [
          512,
          483,
          421,
          479,
          423,
          377,
          382,
          560,
          527,
          410
        ]
      },
      {
        "channel": "Other",
        "sessions": [
          358,
          460,
          370,
          426,
          350,
          531,
          540,
          234,
          302,
          645
        ]
      }
    ]
  }
}