{
  "steps": [
    {
      "name": "Sessions",
      "count": 6959
    },
    {
      "name": "view_item",
      "count": 8370
    },
    {
      "name": "add_to_cart",
      "count": 281
    },
    {
      "name": "begin_checkout",
      "count": 92
    },
    {
      "name": "purchase",
      "count": 55
    }
  ],
  "weeks": [],
  "collections": [
    {
      "path": "/collections/5月6日販売開始",
      "sessions": 627,
      "pdp_reached": 195,
      "pdp_reach": 31.10047846889952
    },
    {
      "path": "/collections/all",
      "sessions": 332,
      "pdp_reached": 128,
      "pdp_reach": 38.55421686746988
    },
    {
      "path": "/collections/setup",
      "sessions": 80,
      "pdp_reached": 31,
      "pdp_reach": 38.75
    },
    {
      "path": "/collections/shortsleeve-t-shirts-2",
      "sessions": 60,
      "pdp_reached": 14,
      "pdp_reach": 23.333333333333332
    },
    {
      "path": "/collections/new",
      "sessions": 48,
      "pdp_reached": 10,
      "pdp_reach": 20.833333333333332
    },
    {
      "path": "/collections/pants",
      "sessions": 45,
      "pdp_reached": 15,
      "pdp_reach": 33.333333333333336
    },
    {
      "path": "/collections/tailored-jacket",
      "sessions": 32,
      "pdp_reached": 2,
      "pdp_reach": 6.25
    }
  ],
  "products_top5": [
    {
      "name": "KOKAGE/テーパードパンツ",
      "qty": 5,
      "revenue": 68750
    },
    {
      "name": "無地半袖Tシャツ",
      "qty": 12,
      "revenue": 66000
    },
    {
      "name": "ストレッチストライプ/半袖シャツ",
      "qty": 5,
      "revenue": 66000
    },
    {
      "name": "KOKAGE/オーバー半袖プルオーバー",
      "qty": 6,
      "revenue": 59400
    },
    {
      "name": "KOKAGE/テーラードジャケット",
      "qty": 3,
      "revenue": 56100
    }
  ]
}