{
  "steps": [
    {
      "name": "Sessions",
      "count": 5172
    },
    {
      "name": "view_item",
      "count": 6726
    },
    {
      "name": "add_to_cart",
      "count": 243
    },
    {
      "name": "begin_checkout",
      "count": 78
    },
    {
      "name": "purchase",
      "count": 47
    }
  ],
  "weeks": [
    {
      "week": "2026-W10",
      "items_per_session": 0,
      "cvr": 0.0024
    },
    {
      "week": "2026-W11",
      "items_per_session": 0,
      "cvr": 0.0067
    },
    {
      "week": "2026-W12",
      "items_per_session": 0,
      "cvr": 0.0045
    },
    {
      "week": "2026-W13",
      "items_per_session": 0,
      "cvr": 0.0036
    },
    {
      "week": "2026-W14",
      "items_per_session": 0,
      "cvr": 0.005
    },
    {
      "week": "2026-W15",
      "items_per_session": 0,
      "cvr": 0.005
    },
    {
      "week": "2026-W16",
      "items_per_session": 0,
      "cvr": 0.0038
    },
    {
      "week": "2026-W17",
      "items_per_session": 0,
      "cvr": 0.0055
    },
    {
      "week": "2026-W18",
      "items_per_session": 0,
      "cvr": 0.0035
    },
    {
      "week": "2026-W19",
      "items_per_session": 0,
      "cvr": 0.0049
    },
    {
      "week": "2026-W20",
      "items_per_session": 0,
      "cvr": 0.0083
    },
    {
      "week": "2026-W21",
      "items_per_session": 0,
      "cvr": 0.0049
    }
  ],
  "collections": [
    {
      "path": "/collections/all",
      "sessions": 231,
      "pdp_reached": 93,
      "pdp_reach": 40.25974025974026
    },
    {
      "path": "/collections/setup",
      "sessions": 52,
      "pdp_reached": 18,
      "pdp_reach": 34.61538461538461
    },
    {
      "path": "/collections/26ss_workitems_2",
      "sessions": 45,
      "pdp_reached": 3,
      "pdp_reach": 6.666666666666667
    },
    {
      "path": "/collections/shortsleeve-t-shirts-2",
      "sessions": 43,
      "pdp_reached": 14,
      "pdp_reach": 32.55813953488372
    },
    {
      "path": "/collections/pants",
      "sessions": 42,
      "pdp_reached": 5,
      "pdp_reach": 11.904761904761905
    },
    {
      "path": "/collections/new",
      "sessions": 41,
      "pdp_reached": 10,
      "pdp_reach": 24.390243902439025
    },
    {
      "path": "/collections/tailored-jacket",
      "sessions": 33,
      "pdp_reached": 3,
      "pdp_reach": 9.090909090909092
    }
  ],
  "products_top5": [
    {
      "name": "KOKAGE/半袖開襟シャツ",
      "qty": 4,
      "revenue": 48400
    },
    {
      "name": "KOKAGE/ジョガーパンツ",
      "qty": 3,
      "revenue": 41250
    },
    {
      "name": "NOBIRU360°/ジョガーパンツ",
      "qty": 3,
      "revenue": 39600
    },
    {
      "name": "ハイストレッチ半袖ポロシャツ",
      "qty": 3,
      "revenue": 31350
    },
    {
      "name": "NOBIRU360°PREMIUM/半袖ポロシャツ",
      "qty": 2,
      "revenue": 30800
    }
  ]
}