{
  "last_updated": "2026-07-02 09:04 JST",
  "flows": [
    {
      "flow_id": "RRZXcL",
      "name": "レビューリクエスト",
      "current_7d": {
        "recipients": 34.0,
        "opens": 19.0,
        "clicks": 3.0,
        "convs": 0,
        "rev": 0.0,
        "open_rate": 0.5588235294117647,
        "click_rate": 0.08823529411764706,
        "conv_rate": 0.0
      },
      "previous_7d": {
        "recipients": 74.0,
        "opens": 46.0,
        "clicks": 11.0,
        "convs": 1.0,
        "rev": 28270.0,
        "open_rate": 0.6216216216216216,
        "click_rate": 0.14864864864864866,
        "conv_rate": 0.013513513513513514
      },
      "current_30d": {
        "recipients": 309.0,
        "opens": 177.0,
        "clicks": 25.0,
        "convs": 3.0,
        "rev": 70620.0,
        "open_rate": 0.5728155339805825,
        "click_rate": 0.08090614886731391,
        "conv_rate": 0.009708737864077669
      },
      "previous_30d": {
        "recipients": 331.0,
        "opens": 198.0,
        "clicks": 27.0,
        "convs": 4.0,
        "rev": 86900.0,
        "open_rate": 0.5981873111782477,
        "click_rate": 0.08157099697885196,
        "conv_rate": 0.012084592145015106
      },
      "annual": {
        "recipients": 1212.0,
        "opens": 672.0,
        "clicks": 102.0,
        "convs": 7.0,
        "rev": 157520.0,
        "open_rate": 0.5544554455445545,
        "click_rate": 0.08415841584158416,
        "conv_rate": 0.005775577557755775
      },
      "wow_pct": -100.0,
      "mom_pct": -18.734177215189874,
      "open_alert": "green",
      "wow_alert": "red",
      "mom_alert": "yellow",
      "rpr_30d": 228.54368932038835
    },
    {
      "flow_id": "SufE4T",
      "name": "カゴ落ちメール",
      "current_7d": {
        "recipients": 46.0,
        "opens": 17.0,
        "clicks": 3.0,
        "convs": 1.0,
        "rev": 7205.0,
        "open_rate": 0.3695652173913043,
        "click_rate": 0.06521739130434782,
        "conv_rate": 0.021739130434782608
      },
      "previous_7d": {
        "recipients": 72.0,
        "opens": 17.0,
        "clicks": 2.0,
        "convs": 2.0,
        "rev": 50600.0,
        "open_rate": 0.2361111111111111,
        "click_rate": 0.027777777777777776,
        "conv_rate": 0.027777777777777776
      },
      "current_30d": {
        "recipients": 377.0,
        "opens": 91.0,
        "clicks": 15.0,
        "convs": 9.0,
        "rev": 282865.0,
        "open_rate": 0.2413793103448276,
        "click_rate": 0.03978779840848806,
        "conv_rate": 0.023872679045092837
      },
      "previous_30d": {
        "recipients": 380.0,
        "opens": 95.0,
        "clicks": 24.0,
        "convs": 8.0,
        "rev": 155870.0,
        "open_rate": 0.25,
        "click_rate": 0.06315789473684211,
        "conv_rate": 0.021052631578947368
      },
      "annual": {
        "recipients": 1408.0,
        "opens": 320.0,
        "clicks": 61.0,
        "convs": 31.0,
        "rev": 668745.0,
        "open_rate": 0.22727272727272727,
        "click_rate": 0.04332386363636364,
        "conv_rate": 0.022017045454545456
      },
      "wow_pct": -85.76086956521739,
      "mom_pct": 81.47494707127734,
      "open_alert": "yellow",
      "wow_alert": "red",
      "mom_alert": "green",
      "rpr_30d": 750.3050397877984
    },
    {
      "flow_id": "VLMvyW",
      "name": "Review follow-up - Klaviyo Reviews",
      "current_7d": {
        "recipients": 1.0,
        "opens": 1.0,
        "clicks": 0,
        "convs": 0,
        "rev": 0.0,
        "open_rate": 1.0,
        "click_rate": 0.0,
        "conv_rate": 0.0
      },
      "previous_7d": {
        "recipients": 1.0,
        "opens": 0,
        "clicks": 0,
        "convs": 0,
        "rev": 0.0,
        "open_rate": 0.0,
        "click_rate": 0.0,
        "conv_rate": 0.0
      },
      "current_30d": {
        "recipients": 6.0,
        "opens": 2.0,
        "clicks": 1.0,
        "convs": 0,
        "rev": 0.0,
        "open_rate": 0.3333333333333333,
        "click_rate": 0.16666666666666666,
        "conv_rate": 0.0
      },
      "previous_30d": {
        "recipients": 6.0,
        "opens": 5.0,
        "clicks": 2.0,
        "convs": 0,
        "rev": 0.0,
        "open_rate": 0.8333333333333334,
        "click_rate": 0.3333333333333333,
        "conv_rate": 0.0
      },
      "annual": {
        "recipients": 27.0,
        "opens": 19.0,
        "clicks": 5.0,
        "convs": 0,
        "rev": 0.0,
        "open_rate": 0.7037037037037037,
        "click_rate": 0.18518518518518517,
        "conv_rate": 0.0
      },
      "wow_pct": null,
      "mom_pct": null,
      "open_alert": "green",
      "wow_alert": "neutral",
      "mom_alert": "neutral",
      "rpr_30d": 0.0
    }
  ],
  "totals": {
    "rev_7d": 7205.0,
    "rev_7d_prev": 78870.0,
    "rev_30d": 353485.0,
    "rev_30d_prev": 242770.0,
    "rev_365d": 826265.0,
    "wow_pct": -90.86471408647141,
    "mom_pct": 45.604893520616216,
    "wow_alert": "red",
    "mom_alert": "green"
  },
  "alerts": [
    {
      "level": "red",
      "flow": "レビューリクエスト",
      "kind": "wow_drop",
      "value": -100.0,
      "msg": "売上 WoW -100.0% (前週比 -20% 以下) — リスト健全性 / 件名変更 / 配信時刻を確認"
    },
    {
      "level": "red",
      "flow": "カゴ落ちメール",
      "kind": "wow_drop",
      "value": -85.76086956521739,
      "msg": "売上 WoW -85.8% (前週比 -20% 以下) — リスト健全性 / 件名変更 / 配信時刻を確認"
    }
  ],
  "legend": {
    "open_rate": {
      "green": ">=0.25",
      "yellow": "0.15-0.25",
      "red": "<0.15"
    },
    "change_pct": {
      "green": ">=-5",
      "yellow": "-20 to -5",
      "red": "<-20"
    },
    "alert_min_recipients": 50,
    "attribution_window_days": 5
  }
}